Serializers/__init__.py
Serializers/base_serializer.py
Serializers/dict_serializer.py
Serializers/json_serializer.py
Serializers/serializers_factory.py
Serializers/type_constants.py
Serializers/xml_serializer.py
SavonchikSerializer-1.0.dist-info/METADATA
SavonchikSerializer-1.0.dist-info/WHEEL
SavonchikSerializer-1.0.dist-info/top_level.txt
SavonchikSerializer-1.0.dist-info/RECORD
